README.rst
setup.py
mycsv/__init__.py
mycsv/cli.py
mycsv.egg-info/PKG-INFO
mycsv.egg-info/SOURCES.txt
mycsv.egg-info/dependency_links.txt
mycsv.egg-info/entry_points.txt
mycsv.egg-info/requires.txt
mycsv.egg-info/top_level.txt