Metadata-Version: 1.1
Name: mycsv
Version: 0.1.3
Summary: Script to export query results into local CSV files
Home-page: https://github.com/osantana/mycsv
Author: Osvaldo Santana Neto
Author-email: UNKNOWN
License: BSD
Download-URL: https://github.com/osantana/mycsv/tarball/0.1.3
Platform: UNKNOWN
Classifier: Development Status :: 5 - Production/Stable
Classifier: Environment :: Console
Classifier: Intended Audience :: Developers
Classifier: Intended Audience :: System Administrators
Classifier: License :: OSI Approved :: BSD License
Classifier: Operating System :: MacOS :: MacOS X
Classifier: Operating System :: Microsoft :: Windows
Classifier: Operating System :: POSIX
Classifier: Programming Language :: Python
Classifier: Programming Language :: Python :: 2
Classifier: Topic :: Database
Classifier: Topic :: Utilities
